{
  "notFound": {
    "title": "Página no encontrada",
    "description": "La página que buscas no existe.",
    "linkLabel": "Volver a la página de inicio",
    "linkHref": "/"
  },
  "sitemap": {
    "sections": [
      {
        "label": "Inicio",
        "link": "src/content/pages/index.mdx"
      },
      {
        "label": "About",
        "link": "src/content/pages/sobre-nosotros.mdx"
      },
      {
        "label": "Artistas",
        "link": "src/content/pages/artistas.mdx"
      },
      {
        "label": "Albums",
        "link": "src/content/pages/discos.mdx"
      },
      {
        "label": "Playlists"
      }
    ]
  }
}
